taurokalkas/__init__.py
taurokalkas/calc.py
kalktastau123-0.3.dist-info/LICENSE
kalktastau123-0.3.dist-info/METADATA
kalktastau123-0.3.dist-info/WHEEL
kalktastau123-0.3.dist-info/top_level.txt
kalktastau123-0.3.dist-info/RECORD
