Metadata-Version: 2.1
Name: kalktastau123
Version: 0.3
Summary: tau
Author: tauras
Author-email: tauro@gmail.com
Classifier: Programming Language :: Python :: 3
Classifier: License :: OSI Approved :: MIT License
Classifier: Operating System :: OS Independent
License-File: LICENSE
